setigen/__init__.py
setigen/_version.py
setigen/cadence.py
setigen/dedrift.py
setigen/distributions.py
setigen/fil_utils.py
setigen/frame.py
setigen/frame_utils.py
setigen/integrate.py
setigen/normalize.py
setigen/plots.py
setigen/sample_from_obs.py
setigen/slice.py
setigen/spectrum.py
setigen/split_utils.py
setigen/stats.py
setigen/time_freq_utils.py
setigen/timeseries.py
setigen/unit_utils.py
setigen/utils.py
setigen/waterfall_utils.py
setigen/assets/sample.fil
setigen/assets/sample_noise_params.npy
setigen/funcs/__init__.py
setigen/funcs/bp_profiles.py
setigen/funcs/f_profiles.py
setigen/funcs/func_utils.py
setigen/funcs/paths.py
setigen/funcs/scint_profiles.py
setigen/funcs/t_profiles.py
setigen/voltage/__init__.py
setigen/voltage/antenna.py
setigen/voltage/backend.py
setigen/voltage/data_stream.py
setigen/voltage/header_template.txt
setigen/voltage/level_utils.py
setigen/voltage/polyphase_filterbank.py
setigen/voltage/quantization.py
setigen/voltage/raw_utils.py
setigen/voltage/waterfall.py
setigen-2.7.0.dist-info/LICENSE
setigen-2.7.0.dist-info/METADATA
setigen-2.7.0.dist-info/WHEEL
setigen-2.7.0.dist-info/dependency_links.txt
setigen-2.7.0.dist-info/top_level.txt
setigen-2.7.0.dist-info/RECORD
