Metadata-Version: 2.1
Name: setigen
Version: 2.7.0
Summary: SETI radio signal generator
Home-page: https://github.com/bbrzycki/setigen
Author: Bryan Brzycki
Author-email: bbrzycki@berkeley.edu
Project-URL: Documentation, https://setigen.readthedocs.io/en/latest/
Project-URL: Source, https://github.com/bbrzycki/setigen
Classifier: Programming Language :: Python :: 3
Classifier: License :: OSI Approved :: MIT License
Classifier: Operating System :: OS Independent
License-File: LICENSE
Requires-Dist: numpy (>=1.21.6)
Requires-Dist: scipy (>=1.8.0)
Requires-Dist: astropy (>=5.0.4)
Requires-Dist: blimpy (>=2.1.4)
Requires-Dist: matplotlib (>=3.8.0)
Requires-Dist: tqdm (>=4.47.0)
Requires-Dist: sphinx-rtd-theme (>=0.4.3)
Requires-Dist: pytest-cov (>=4.1.0)
